setup.py
bit_array/__init__.py
bit_array/bit_array.py
bit_array.egg-info/PKG-INFO
bit_array.egg-info/SOURCES.txt
bit_array.egg-info/dependency_links.txt
bit_array.egg-info/top_level.txt
test/test_bitarray.py